setup.py
udacity_gaus_bin_dist/Binomialdistribution.py
udacity_gaus_bin_dist/Gaussiandistribution.py
udacity_gaus_bin_dist/Generaldistribution.py
udacity_gaus_bin_dist/__init__.py
udacity_gaus_bin_dist.egg-info/PKG-INFO
udacity_gaus_bin_dist.egg-info/SOURCES.txt
udacity_gaus_bin_dist.egg-info/dependency_links.txt
udacity_gaus_bin_dist.egg-info/not-zip-safe
udacity_gaus_bin_dist.egg-info/top_level.txt