Metadata-Version: 1.0
Name: udacity-gaus-bin-dist
Version: 0.1
Summary: Gaussian and Binomial distributions
Home-page: UNKNOWN
Author: Nils Mayat
Author-email: UNKNOWN
License: UNKNOWN
Platform: UNKNOWN
